Metadata-Version: 1.2
Name: lazypkg
Version: 1.4
Summary: lazy import modules and subpackages
Home-page: https://github.com/yoelcortes/lazypkg
Author: Yoel Cortes-Pena
Author-email: yoelcortes@gmail.com
License: MIT
Download-URL: https://github.com/yoelcortes/lazypkg.git
Keywords: lazy import modules and subpackages package tools
Platform: Windows
Platform: Mac
Platform: Linux
Classifier: Development Status :: 5 - Production/Stable
Classifier: Environment :: Console
Classifier: License :: OSI Approved :: MIT License
Classifier: Programming Language :: Python :: 3.6
Classifier: Programming Language :: Python :: 3.7
Classifier: Topic :: Software Development :: Libraries :: Python Modules
Requires-Python: >=3.6
